{
  "version": "7",
  "dialect": "postgresql",
  "entries": [
    {
      "idx": 0,
      "version": "7",
      "when": 1764229815704,
      "tag": "0000_purple_captain_britain",
      "breakpoints": true
    },
    {
      "idx": 1,
      "version": "7",
      "when": 1764570392014,
      "tag": "0001_dazzling_epoch",
      "breakpoints": true
    },
    {
      "idx": 2,
      "version": "7",
      "when": 1764665826564,
      "tag": "0002_tiresome_argent",
      "breakpoints": true
    },
    {
      "idx": 3,
      "version": "7",
      "when": 1765514977622,
      "tag": "0003_shiny_greymalkin",
      "breakpoints": true
    }
  ]
}